{
  "compounds": [
    {
      "name": "milk",
      "matter_state": "liquid",
      "has_item": false,
      "has_fluid": true,
      "description": "It does a body good.",
      "color": "FAFAFA",
      "components": [
        {
          "name": "hydrogen",
          "count": 25
        },
        {
          "name": "carbon",
          "count": 10
        },
        {
          "name": "oxygen"
        },
        {
          "name": "nitrogen",
          "count": 3
        }
      ]
    },
    {
      "name": "lava",
      "matter_state": "liquid",
      "has_item": false,
      "has_fluid": true,
      "description": "OUCH OUCH OUCH!",
      "color": "FF0000",
      "components": [
        {
          "name": "potassium",
          "count": 1
        },
        {
          "name": "sodium",
          "count": 1
        },
        {
          "name": "magnesium",
          "count": 1
        },
        {
          "name": "silicon",
          "count": 3
        },
        {
          "name": "calcium",
          "count": 1
        },
        {
          "name": "aluminum",
          "count": 1
        },
        {
          "name": "oxygen",
          "count": 525
        }
      ],
      "effect": [
        {
          "location": "minecraft:nausea",
          "duration": "600",
          "amplifier": 2
        },
        {
          "location": "minecraft:slowness",
          "duration": "600",
          "amplifier": 0
        },
        {
          "location": "minecraft:weakness",
          "duration": "600",
          "amplifier": 0
        }
      ]
    }
  ]
}